poetry_quick_start/__init__.py
poetry_quick_start-0.1.0.dist-info/METADATA
poetry_quick_start-0.1.0.dist-info/WHEEL
poetry_quick_start-0.1.0.dist-info/RECORD
